prettyfy/ANSI_Colorizer.py
prettyfy/CliUtils.py
prettyfy/ColorSet.py
prettyfy/Decor.py
prettyfy/MenuDriver.py
prettyfy/Win7_Colorizer.py
prettyfy/__init__.py
prettyfy/safe_exec.py
prettyfy-0.2.dist-info/LICENSE
prettyfy-0.2.dist-info/METADATA
prettyfy-0.2.dist-info/WHEEL
prettyfy-0.2.dist-info/entry_points.txt
prettyfy-0.2.dist-info/top_level.txt
prettyfy-0.2.dist-info/RECORD
