Metadata-Version: 2.1
Name: prettyfy
Version: 0.2
Summary: A package of the students to beautify their console
Home-page: https://github.com/Shanmukh-dev/Prettyfy-Package
Author: T S Shannmukh Vshtav
License-File: LICENSE
Requires-Dist: windows-curses ; sys_platform == "win32"
